logutils/__init__.py
logutils/api.py
logutils/py.typed
logutils/pytest_plugin.py
pylogutils-0.1.4.data/scripts/README.md
pylogutils-0.1.4.dist-info/METADATA
pylogutils-0.1.4.dist-info/WHEEL
pylogutils-0.1.4.dist-info/top_level.txt
pylogutils-0.1.4.dist-info/RECORD
