Metadata-Version: 2.1
Name: pylogutils
Version: 0.1.4
Summary: Better logging made easy with support for structlog and the standard logging module.
Home-page: https://github.com/bbugyi200/logutils
Author: Bryan M Bugyi
Author-email: bryanbugyi34@gmail.com
License: MIT license
Platform: UNKNOWN
Classifier: Development Status :: 3 - Alpha
Classifier: Intended Audience :: Developers
Classifier: License :: OSI Approved :: MIT License
Classifier: Natural Language :: English
Classifier: Programming Language :: Python :: 3
Classifier: Programming Language :: Python :: 3.7
Classifier: Programming Language :: Python :: 3.8
Classifier: Programming Language :: Python :: 3.9
Requires-Python: >=3.7
Requires-Dist: bugyi.lib (>=0.4.0)
Requires-Dist: colorama
Requires-Dist: pydantic
Requires-Dist: structlog
